Workbook

Sheet README
A1: Keplar growth model (editable)
A3: Purpose: show what traffic, conversion, retention and cost structure each revenue milestone would require. Goals, not forecasts. Nothing here says revenue has been achieved.
A4: Sheets: CostPerTask (real routing + list prices -> cost per successful task) | Model (inputs, three scenarios, 60 months) | Milestones | Profit1M | Illustration | Proposals | Assumptions.
A5: Colours: blue text = input you can change. Yellow fill = unsupported assumption. Green fill = verified against a dated source. Black = formula.
A6: Verified (2026-10-03): Whop billed amounts via the Whop API ($19.99 / $44.99 / $99.99; the site shows $20 / $45 / $99), Whop fees (docs.whop.com/fees), OpenRouter 5.5% credit fee, free-model request limits, the repo's routing and list prices, Vercel Hobby = non-commercial.
A7: Definitions: MRR = billed subscription revenue per month. ARR run-rate = MRR x 12, before any expense. Cash collected includes one-time sales. Lifetime deals are one-time cash and are never part of MRR or ARR.
A8: Simplifications: a new payer in month m is billed in month m; churn applies to the previous month's base; conversion is within the month; Free users cost $0 USD but share a limited pool of free-model requests; income tax and sales tax are not modeled.
A9: Not modeled: annual plans (none exist), taxes, Whop add-on fees (orchestration, billing, tax are optional extras), seasonality, price changes.

Sheet Milestones
A1: Milestones: what each level needs (targets, not forecasts)
A2: Left: when each scenario reaches the milestone. Below: the steady-state requirement, i.e. how many customers, new payers per month and qualified visits per month it takes to HOLD that MRR given the scenario's churn and conversion. Every conversion rate is an unsupported assumption until experiments E1-E5 report.
A4: Scenario / milestone | B4: Month reached | C4: MRR then | D4: Paying customers | E4: Qualified visits / mo | F4: New payers / mo | G4: Visit to paid
A5: Conservative
A6: =Model!A67 -> $1,000 MRR | B6: =Model!B67 -> not in 60 mo | C6: =Model!C67 -> - | D6: =Model!D67 -> - | E6: =Model!E67 -> - | F6: =Model!F67 -> - | G6: =Model!G67 -> -
A7: =Model!A68 -> $10,000 MRR | B7: =Model!B68 -> not in 60 mo | C7: =Model!C68 -> - | D7: =Model!D68 -> - | E7: =Model!E68 -> - | F7: =Model!F68 -> - | G7: =Model!G68 -> -
A8: =Model!A69 -> $100,000 MRR | B8: =Model!B69 -> not in 60 mo | C8: =Model!C69 -> - | D8: =Model!D69 -> - | E8: =Model!E69 -> - | F8: =Model!F69 -> - | G8: =Model!G69 -> -
A9: =Model!A70 -> $1M ARR run-rate ($83,333 MRR) | B9: =Model!B70 -> not in 60 mo | C9: =Model!C70 -> - | D9: =Model!D70 -> - | E9: =Model!E70 -> - | F9: =Model!F70 -> - | G9: =Model!G70 -> -
A10: =Model!A71 -> $5M ARR run-rate ($416,667 MRR) | B10: =Model!B71 -> not in 60 mo | C10: =Model!C71 -> - | D10: =Model!D71 -> - | E10: =Model!E71 -> - | F10: =Model!F71 -> - | G10: =Model!G71 -> -
A12: Base
A13: =Model!A132 -> $1,000 MRR | B13: =Model!B132 -> 21 | C13: =Model!C132 -> 1105.5848 | D13: =Model!D132 -> 27.982264 | E13: =Model!E132 -> 10091.25 | F13: =Model!F132 -> 4.5410625 | G13: =Model!G132 -> 0.00045
A14: =Model!A133 -> $10,000 MRR | B14: =Model!B133 -> 44 | C14: =Model!C133 -> 10264.743 | D14: =Model!D133 -> 257.97741 | E14: =Model!E133 -> 90360.104 | F14: =Model!F133 -> 40.662047 | G14: =Model!G133 -> 0.00045
A15: =Model!A134 -> $100,000 MRR | B15: =Model!B134 -> not in 60 mo | C15: =Model!C134 -> - | D15: =Model!D134 -> - | E15: =Model!E134 -> - | F15: =Model!F134 -> - | G15: =Model!G134 -> -
A16: =Model!A135 -> $1M ARR run-rate ($83,333 MRR) | B16: =Model!B135 -> not in 60 mo | C16: =Model!C135 -> - | D16: =Model!D135 -> - | E16: =Model!E135 -> - | F16: =Model!F135 -> - | G16: =Model!G135 -> -
A17: =Model!A136 -> $5M ARR run-rate ($416,667 MRR) | B17: =Model!B136 -> not in 60 mo | C17: =Model!C136 -> - | D17: =Model!D136 -> - | E17: =Model!E136 -> - | F17: =Model!F136 -> - | G17: =Model!G136 -> -
A19: Ambitious
A20: =Model!A197 -> $1,000 MRR | B20: =Model!B197 -> 4 | C20: =Model!C197 -> 1251.9482 | D20: =Model!D197 -> 28.099273 | E20: =Model!E197 -> 5926.176 | F20: =Model!F197 -> 9.126311 | G20: =Model!G197 -> 0.00154
A21: =Model!A198 -> $10,000 MRR | B21: =Model!B198 -> 16 | C21: =Model!C198 -> 11080.54 | D21: =Model!D198 -> 243.07668 | E21: =Model!E198 -> 28551.752 | F21: =Model!F198 -> 43.969698 | G21: =Model!G198 -> 0.00154
A22: =Model!A199 -> $100,000 MRR | B22: =Model!B199 -> 33 | C22: =Model!C199 -> 108693.21 | D22: =Model!D199 -> 2368.6613 | E22: =Model!E199 -> 264859.3 | F22: =Model!F199 -> 407.88333 | G22: =Model!G199 -> 0.00154
A23: =Model!A200 -> $1M ARR run-rate ($83,333 MRR) | B23: =Model!B200 -> 31 | C23: =Model!C200 -> 83535.885 | D23: =Model!D200 -> 1820.8385 | E23: =Model!E200 -> 203800.63 | F23: =Model!F200 -> 313.85298 | G23: =Model!G200 -> 0.00154
A24: =Model!A201 -> $5M ARR run-rate ($416,667 MRR) | B24: =Model!B201 -> 57 | C24: =Model!C201 -> 423842.3 | D24: =Model!D201 -> 8831.0636 | E24: =Model!E201 -> 400000 | F24: =Model!F201 -> 616 | G24: =Model!G201 -> 0.00154
A26: Steady-state requirement (holds the MRR level, per scenario)
A27: Target | B27: Scenario | C27: MRR target | D27: Blended billed ARPU | E27: Customers needed | F27: Blended monthly churn (by customers) | G27: New payers / month to hold | H27: Visit to paid | I27: Qualified visits / month to hold | J27: Of which: visits needed for growth (+10%/mo)
A28: $1,000 MRR | B28: Conservative | C28: 1000 | D28: =(Model!$C$28*Model!$C$6+Model!$C$29*Model!$C$7+Model!$C$30*Model!$C$8)*(1+Model!$C$38) -> 32.59 | E28: =C28/D28 -> 30.684259 | F28: =Model!$C$28*Model!$C$35+Model!$C$29*Model!$C$36+Model!$C$30*Model!$C$37 -> 0.1046 | G28: =E28*F28 -> 3.2095735 | H28: =Model!$C$25*Model!$C$26*Model!$C$27 -> 0.00013125 | I28: =G28/H28 -> 24453.893 | J28: =(G28+E28*0.1/(1+0.1))/H28 -> 45707.06
A29: $1,000 MRR | B29: Base | C29: 1000 | D29: =(Model!$D$28*Model!$D$6+Model!$D$29*Model!$D$7+Model!$D$30*Model!$D$8)*(1+Model!$D$38) -> 37.4748 | E29: =C29/D29 -> 26.684599 | F29: =Model!$D$28*Model!$D$35+Model!$D$29*Model!$D$36+Model!$D$30*Model!$D$37 -> 0.075 | G29: =E29*F29 -> 2.0013449 | H29: =Model!$D$25*Model!$D$26*Model!$D$27 -> 0.00045 | I29: =G29/H29 -> 4447.4331 | J29: =(G29+E29*0.1/(1+0.1))/H29 -> 9838.2611
A30: $1,000 MRR | B30: Ambitious | C30: 1000 | D30: =(Model!$E$28*Model!$E$6+Model!$E$29*Model!$E$7+Model!$E$30*Model!$E$8)*(1+Model!$E$38) -> 44.0895 | E30: =C30/D30 -> 22.681137 | F30: =Model!$E$28*Model!$E$35+Model!$E$29*Model!$E$36+Model!$E$30*Model!$E$37 -> 0.05675 | G30: =E30*F30 -> 1.2871545 | H30: =Model!$E$25*Model!$E$26*Model!$E$27 -> 0.00154 | I30: =G30/H30 -> 835.81464 | J30: =(G30+E30*0.1/(1+0.1))/H30 -> 2174.7247
A31: $10,000 MRR | B31: Conservative | C31: 10000 | D31: =(Model!$C$28*Model!$C$6+Model!$C$29*Model!$C$7+Model!$C$30*Model!$C$8)*(1+Model!$C$38) -> 32.59 | E31: =C31/D31 -> 306.84259 | F31: =Model!$C$28*Model!$C$35+Model!$C$29*Model!$C$36+Model!$C$30*Model!$C$37 -> 0.1046 | G31: =E31*F31 -> 32.095735 | H31: =Model!$C$25*Model!$C$26*Model!$C$27 -> 0.00013125 | I31: =G31/H31 -> 244538.93 | J31: =(G31+E31*0.1/(1+0.1))/H31 -> 457070.6
A32: $10,000 MRR | B32: Base | C32: 10000 | D32: =(Model!$D$28*Model!$D$6+Model!$D$29*Model!$D$7+Model!$D$30*Model!$D$8)*(1+Model!$D$38) -> 37.4748 | E32: =C32/D32 -> 266.84599 | F32: =Model!$D$28*Model!$D$35+Model!$D$29*Model!$D$36+Model!$D$30*Model!$D$37 -> 0.075 | G32: =E32*F32 -> 20.013449 | H32: =Model!$D$25*Model!$D$26*Model!$D$27 -> 0.00045 | I32: =G32/H32 -> 44474.331 | J32: =(G32+E32*0.1/(1+0.1))/H32 -> 98382.611
A33: $10,000 MRR | B33: Ambitious | C33: 10000 | D33: =(Model!$E$28*Model!$E$6+Model!$E$29*Model!$E$7+Model!$E$30*Model!$E$8)*(1+Model!$E$38) -> 44.0895 | E33: =C33/D33 -> 226.81137 | F33: =Model!$E$28*Model!$E$35+Model!$E$29*Model!$E$36+Model!$E$30*Model!$E$37 -> 0.05675 | G33: =E33*F33 -> 12.871545 | H33: =Model!$E$25*Model!$E$26*Model!$E$27 -> 0.00154 | I33: =G33/H33 -> 8358.1464 | J33: =(G33+E33*0.1/(1+0.1))/H33 -> 21747.247
A34: $100,000 MRR | B34: Conservative | C34: 100000 | D34: =(Model!$C$28*Model!$C$6+Model!$C$29*Model!$C$7+Model!$C$30*Model!$C$8)*(1+Model!$C$38) -> 32.59 | E34: =C34/D34 -> 3068.4259 | F34: =Model!$C$28*Model!$C$35+Model!$C$29*Model!$C$36+Model!$C$30*Model!$C$37 -> 0.1046 | G34: =E34*F34 -> 320.95735 | H34: =Model!$C$25*Model!$C$26*Model!$C$27 -> 0.00013125 | I34: =G34/H34 -> 2445389.3 | J34: =(G34+E34*0.1/(1+0.1))/H34 -> 4570706
A35: $100,000 MRR | B35: Base | C35: 100000 | D35: =(Model!$D$28*Model!$D$6+Model!$D$29*Model!$D$7+Model!$D$30*Model!$D$8)*(1+Model!$D$38) -> 37.4748 | E35: =C35/D35 -> 2668.4599 | F35: =Model!$D$28*Model!$D$35+Model!$D$29*Model!$D$36+Model!$D$30*Model!$D$37 -> 0.075 | G35: =E35*F35 -> 200.13449 | H35: =Model!$D$25*Model!$D$26*Model!$D$27 -> 0.00045 | I35: =G35/H35 -> 444743.31 | J35: =(G35+E35*0.1/(1+0.1))/H35 -> 983826.11
A36: $100,000 MRR | B36: Ambitious | C36: 100000 | D36: =(Model!$E$28*Model!$E$6+Model!$E$29*Model!$E$7+Model!$E$30*Model!$E$8)*(1+Model!$E$38) -> 44.0895 | E36: =C36/D36 -> 2268.1137 | F36: =Model!$E$28*Model!$E$35+Model!$E$29*Model!$E$36+Model!$E$30*Model!$E$37 -> 0.05675 | G36: =E36*F36 -> 128.71545 | H36: =Model!$E$25*Model!$E$26*Model!$E$27 -> 0.00154 | I36: =G36/H36 -> 83581.464 | J36: =(G36+E36*0.1/(1+0.1))/H36 -> 217472.47
A37: $1M ARR | B37: Conservative | C37: 83333.333 | D37: =(Model!$C$28*Model!$C$6+Model!$C$29*Model!$C$7+Model!$C$30*Model!$C$8)*(1+Model!$C$38) -> 32.59 | E37: =C37/D37 -> 2557.0216 | F37: =Model!$C$28*Model!$C$35+Model!$C$29*Model!$C$36+Model!$C$30*Model!$C$37 -> 0.1046 | G37: =E37*F37 -> 267.46446 | H37: =Model!$C$25*Model!$C$26*Model!$C$27 -> 0.00013125 | I37: =G37/H37 -> 2037824.4 | J37: =(G37+E37*0.1/(1+0.1))/H37 -> 3808921.6
A38: $1M ARR | B38: Base | C38: 83333.333 | D38: =(Model!$D$28*Model!$D$6+Model!$D$29*Model!$D$7+Model!$D$30*Model!$D$8)*(1+Model!$D$38) -> 37.4748 | E38: =C38/D38 -> 2223.7166 | F38: =Model!$D$28*Model!$D$35+Model!$D$29*Model!$D$36+Model!$D$30*Model!$D$37 -> 0.075 | G38: =E38*F38 -> 166.77874 | H38: =Model!$D$25*Model!$D$26*Model!$D$27 -> 0.00045 | I38: =G38/H38 -> 370619.43 | J38: =(G38+E38*0.1/(1+0.1))/H38 -> 819855.1
A39: $1M ARR | B39: Ambitious | C39: 83333.333 | D39: =(Model!$E$28*Model!$E$6+Model!$E$29*Model!$E$7+Model!$E$30*Model!$E$8)*(1+Model!$E$38) -> 44.0895 | E39: =C39/D39 -> 1890.0948 | F39: =Model!$E$28*Model!$E$35+Model!$E$29*Model!$E$36+Model!$E$30*Model!$E$37 -> 0.05675 | G39: =E39*F39 -> 107.26288 | H39: =Model!$E$25*Model!$E$26*Model!$E$27 -> 0.00154 | I39: =G39/H39 -> 69651.22 | J39: =(G39+E39*0.1/(1+0.1))/H39 -> 181227.06
A40: $5M ARR | B40: Conservative | C40: 416666.67 | D40: =(Model!$C$28*Model!$C$6+Model!$C$29*Model!$C$7+Model!$C$30*Model!$C$8)*(1+Model!$C$38) -> 32.59 | E40: =C40/D40 -> 12785.108 | F40: =Model!$C$28*Model!$C$35+Model!$C$29*Model!$C$36+Model!$C$30*Model!$C$37 -> 0.1046 | G40: =E40*F40 -> 1337.3223 | H40: =Model!$C$25*Model!$C$26*Model!$C$27 -> 0.00013125 | I40: =G40/H40 -> 10189122 | J40: =(G40+E40*0.1/(1+0.1))/H40 -> 19044608
A41: $5M ARR | B41: Base | C41: 416666.67 | D41: =(Model!$D$28*Model!$D$6+Model!$D$29*Model!$D$7+Model!$D$30*Model!$D$8)*(1+Model!$D$38) -> 37.4748 | E41: =C41/D41 -> 11118.583 | F41: =Model!$D$28*Model!$D$35+Model!$D$29*Model!$D$36+Model!$D$30*Model!$D$37 -> 0.075 | G41: =E41*F41 -> 833.89371 | H41: =Model!$D$25*Model!$D$26*Model!$D$27 -> 0.00045 | I41: =G41/H41 -> 1853097.1 | J41: =(G41+E41*0.1/(1+0.1))/H41 -> 4099275.5
A42: $5M ARR | B42: Ambitious | C42: 416666.67 | D42: =(Model!$E$28*Model!$E$6+Model!$E$29*Model!$E$7+Model!$E$30*Model!$E$8)*(1+Model!$E$38) -> 44.0895 | E42: =C42/D42 -> 9450.4738 | F42: =Model!$E$28*Model!$E$35+Model!$E$29*Model!$E$36+Model!$E$30*Model!$E$37 -> 0.05675 | G42: =E42*F42 -> 536.31439 | H42: =Model!$E$25*Model!$E$26*Model!$E$27 -> 0.00154 | I42: =G42/H42 -> 348256.1 | J42: =(G42+E42*0.1/(1+0.1))/H42 -> 906135.31
A44: Reading it: 'to hold' is the traffic that replaces churned customers; growing needs more. Column J adds the extra new payers needed to keep growing 10% a month at that size. Compare these visit counts with what two founders and a $0 budget can plausibly earn; no audience size is claimed.
A46: Annual summary by scenario (sums of the monthly columns)
A47: Scenario / line | B47: Year 1 | C47: Year 2 | D47: Year 3 | E47: Year 4 | F47: Year 5
A48: Conservative
A49: Net recurring revenue | B49: =SUM(Model!D96:O96) -> 148.25248 | C49: =SUM(Model!P96:AA96) -> 457.76885 | D49: =SUM(Model!AB96:AM96) -> 977.64455 | E49: =SUM(Model!AN96:AY96) -> 1988.8335 | F49: =SUM(Model!AZ96:BK96) -> 4010.6688
A50: One-time sales (never recurring) | B50: =SUM(Model!D97:O97) -> 0 | C50: =SUM(Model!P97:AA97) -> 0 | D50: =SUM(Model!AB97:AM97) -> 0 | E50: =SUM(Model!AN97:AY97) -> 0 | F50: =SUM(Model!AZ97:BK97) -> 0
A51: Gross profit (contribution) | B51: =SUM(Model!D104:O104) -> 117.28328 | C51: =SUM(Model!P104:AA104) -> 361.72383 | D51: =SUM(Model!AB104:AM104) -> 772.10494 | E51: =SUM(Model!AN104:AY104) -> 1570.4738 | F51: =SUM(Model!AZ104:BK104) -> 3166.8998
A52: Operating profit | B52: =SUM(Model!D118:O118) -> -1101.2456 | C52: =SUM(Model!P118:AA118) -> -890.55114 | D52: =SUM(Model!AB118:AM118) -> -537.15911 | E52: =SUM(Model!AN118:AY118) -> 149.28904 | F52: =SUM(Model!AZ118:BK118) -> 1521.3625
A53: MRR at year end | B53: =Model!O91 -> 24.10184 | C53: =Model!AA91 -> 56.7021 | D53: =Model!AM91 -> 117.13625 | E53: =Model!AY91 -> 236.90305 | F53: =Model!BK91 -> 477.19302
A55: Base
A56: Net recurring revenue | B56: =SUM(Model!D161:O161) -> 2308.8368 | C56: =SUM(Model!P161:AA161) -> 10491.797 | D56: =SUM(Model!AB161:AM161) -> 34463.925 | E56: =SUM(Model!AN161:AY161) -> 108712.07 | F56: =SUM(Model!AZ161:BK161) -> 238359.35
A57: One-time sales (never recurring) | B57: =SUM(Model!D162:O162) -> 0 | C57: =SUM(Model!P162:AA162) -> 0 | D57: =SUM(Model!AB162:AM162) -> 0 | E57: =SUM(Model!AN162:AY162) -> 0 | F57: =SUM(Model!AZ162:BK162) -> 0
A58: Gross profit (contribution) | B58: =SUM(Model!D169:O169) -> 1985.517 | C58: =SUM(Model!P169:AA169) -> 9020.0913 | D58: =SUM(Model!AB169:AM169) -> 29625.991 | E58: =SUM(Model!AN169:AY169) -> 93448.9 | F58: =SUM(Model!AZ169:BK169) -> 204853.29
A59: Operating profit | B59: =SUM(Model!D183:O183) -> 633.98985 | C59: =SUM(Model!P183:AA183) -> 7171.9361 | D59: =SUM(Model!AB183:AM183) -> 26323.264 | E59: =SUM(Model!AN183:AY183) -> 85635.455 | F59: =SUM(Model!AZ183:BK183) -> 189772.09
A60: MRR at year end | B60: =Model!O156 -> 414.28159 | C60: =Model!AA156 -> 1492.2596 | D60: =Model!AM156 -> 4776.1799 | E60: =Model!AY156 -> 14824.495 | F60: =Model!BK156 -> 24254.331
A62: Ambitious
A63: Net recurring revenue | B63: =SUM(Model!D226:O226) -> 31374.774 | C63: =SUM(Model!P226:AA226) -> 204521.67 | D63: =SUM(Model!AB226:AM226) -> 1015502.6 | E63: =SUM(Model!AN226:AY226) -> 3145958.6 | F63: =SUM(Model!AZ226:BK226) -> 4726267.6
A64: One-time sales (never recurring) | B64: =SUM(Model!D227:O227) -> 0 | C64: =SUM(Model!P227:AA227) -> 0 | D64: =SUM(Model!AB227:AM227) -> 0 | E64: =SUM(Model!AN227:AY227) -> 0 | F64: =SUM(Model!AZ227:BK227) -> 0
A65: Gross profit (contribution) | B65: =SUM(Model!D234:O234) -> 27666.324 | C65: =SUM(Model!P234:AA234) -> 180329.36 | D65: =SUM(Model!AB234:AM234) -> 895349.83 | E65: =SUM(Model!AN234:AY234) -> 2773480.8 | F65: =SUM(Model!AZ234:BK234) -> 4165680.6
A66: Operating profit | B66: =SUM(Model!D248:O248) -> 25277.254 | C66: =SUM(Model!P248:AA248) -> 171620.55 | D66: =SUM(Model!AB248:AM248) -> 857080.13 | E66: =SUM(Model!AN248:AY248) -> 2661027.5 | F66: =SUM(Model!AZ248:BK248) -> 4004338.2
A67: MRR at year end | B67: =Model!O221 -> 6148.6754 | C67: =Model!AA221 -> 33055.902 | D67: =Model!AM221 -> 161220.97 | E67: =Model!AY221 -> 342008.77 | F67: =Model!BK221 -> 444379

Sheet Model
A1: Keplar revenue and cost model: 60 monthly periods, three scenarios (targets and what-ifs, NOT forecasts)
A2: Blue = input you can edit. Yellow = unsupported assumption (no Keplar data yet). Green = verified against a source on 2026-10-03. Black = formula. Currency USD. MRR/ARR here are billed subscription revenue; lifetime deals never count as recurring.
A4: Input | B4: Unit | C4: Conservative | D4: Base | E4: Ambitious | F4: Evidence | G4: Source / experiment that would validate it
A5: Prices and payment costs (Whop)
A6: Lite: amount Whop bills per month (site shows $20) | B6: $ | C6: 19.99 | D6: =C6 -> 19.99 | E6: =C6 -> 19.99 | F6: VERIFIED | G6: Whop API plan_qpgb6JV0jhQGj renewal price, read 2026-10-03
A7: Plus: billed per month | B7: $ | C7: 44.99 | D7: =C7 -> 44.99 | E7: =C7 -> 44.99 | F7: VERIFIED | G7: Whop API plan_wd9Xs4iDlwvDi
A8: Pro: billed per month (site shows $99) | B8: $ | C8: 99.99 | D8: =C8 -> 99.99 | E8: =C8 -> 99.99 | F8: VERIFIED | G8: Whop API plan_M6ztgSJDucMJA renewal $99.99
A9: Whop card fee, percent of each payment | B9: % | C9: 0.027 | D9: =C9 -> 0.027 | E9: =C9 -> 0.027 | F9: VERIFIED | G9: docs.whop.com/fees, 2026-10-03: 2.7% + $0.30 domestic card
A10: Whop card fee, fixed per payment | B10: $ | C10: 0.3 | D10: =C10 -> 0.3 | E10: =C10 -> 0.3 | F10: VERIFIED | G10: docs.whop.com/fees
A11: Share of payments that are international cards | B11: % | C11: 0.3 | D11: =C11 -> 0.3 | E11: =C11 -> 0.3 | F11: ASSUMPTION | G11: No payment data yet. E8: read the real mix from Whop after the first 20 payments
A12: Extra fee on international cards + FX (1.5% + 1.0%) | B12: % | C12: 0.025 | D12: =C12 -> 0.025 | E12: =C12 -> 0.025 | F12: VERIFIED | G12: docs.whop.com/fees (international +1.5%, currency conversion +1%)
A13: Dispute fee per chargeback | B13: $ | C13: 15 | D13: =C13 -> 15 | E13: =C13 -> 15 | F13: VERIFIED | G13: docs.whop.com/fees
A14: Share of payments disputed | B14: % | C14: 0.004 | D14: 0.002 | E14: 0.001 | F14: ASSUMPTION | G14: Track from Whop: disputes / payments
A15: Refunds, share of billed revenue (fees are not returned) | B15: % | C15: 0.05 | D15: 0.03 | E15: 0.02 | F15: ASSUMPTION | G15: Track refunds in /admin/growth; E8
A16: Share of new paying customers who get an introductory discount | B16: % | C16: 0.15 | D16: 0.1 | E16: 0.05 | F16: ASSUMPTION | G16: Only if a promo is approved (OFFER.md); none is live
A17: Discount depth on that first payment | B17: % | C17: 0.2 | D17: =C17 -> 0.2 | E17: =C17 -> 0.2 | F17: ASSUMPTION | G17: OFFER.md proposal; not live
A18: OpenRouter fee on credit purchases (provider spend) | B18: % | C18: 0.055 | D18: =C18 -> 0.055 | E18: =C18 -> 0.055 | F18: VERIFIED | G18: OpenRouter FAQ/pricing: 5.5% fee on credit purchases, 2026-10-03
A19: Acquisition and conversion funnel (no Keplar data yet: everything here is an ASSUMPTION)
A20: Qualified visits in month 1 (organic + community, $0 spend) | B20: visits/mo | C20: 500 | D20: 1500 | E20: 4000 | F20: ASSUMPTION | G20: Qualified = reached a public page and stayed. E1/E2: measure from /admin/growth after the first 4 weeks
A21: Monthly growth of qualified visits | B21: %/mo | C21: 0.06 | D21: 0.1 | E21: 0.14 | F21: ASSUMPTION | G21: Needs search + demo content to compound; E1, E2
A22: Ceiling on organic visits (founder time / channel size) | B22: visits/mo | C22: 40000 | D22: 120000 | E22: 400000 | F22: ASSUMPTION | G22: Unknown audience sizes; no figure is claimed
A23: Paid acquisition spend per month (PROPOSAL only; $0 budget today) | B23: $/mo | C23: 0 | D23: =C23 -> 0 | E23: =C23 -> 0 | F23: VERIFIED | G23: Budget is $0. Change only after a budget, loss limit and authorization exist
A24: Cost per qualified visit if paid is ever used | B24: $ | C24: 1.5 | D24: =C24 -> 1.5 | E24: =C24 -> 1.5 | F24: ASSUMPTION | G24: Not tested; E11 would measure it with a capped test
A25: Visit to account created | B25: % | C25: 0.015 | D25: 0.025 | E25: 0.04 | F25: ASSUMPTION | G25: Anonymous use is allowed, so some visitors never sign up. Measure: seo_events landing_view vs signup_complete
A26: Account to activated (answer, then a deliberate action) | B26: % | C26: 0.35 | D26: 0.45 | E26: 0.55 | F26: ASSUMPTION | G26: Definition in docs/growth/ACTIVATION.md. Measure: growth_events
A27: Activated user to paying within the month | B27: % | C27: 0.025 | D27: 0.04 | E27: 0.07 | F27: ASSUMPTION | G27: Price is >2x single-model subscriptions at Plus. E4/E5 test the offer
A28: New payers choosing Lite | B28: % | C28: 0.65 | D28: 0.55 | E28: 0.45 | F28: ASSUMPTION | G28: Measure plan mix at the first 10 payers
A29: New payers choosing Plus | B29: % | C29: 0.28 | D29: 0.35 | E29: 0.4 | F29: ASSUMPTION
A30: New payers choosing Pro (remainder) | B30: % | C30: =1-C28-C29 -> 0.07 | D30: =1-D28-D29 -> 0.1 | E30: =1-E28-E29 -> 0.15 | F30: FORMULA | G30: Formula: 1 minus Lite minus Plus
A31: Referral: invites sent per paying customer per month (OFF) | B31: per mo | C31: 0 | D31: =C31 -> 0 | E31: =C31 -> 0 | F31: VERIFIED | G31: No reward or invite program is live. Costed proposal in SHARING.md
A32: Referral: invited person creates an account | B32: % | C32: 0.1 | D32: =C32 -> 0.1 | E32: =C32 -> 0.1 | F32: ASSUMPTION | G32: Only relevant if the proposal is approved
A33: Referral: reward cost per converted invitee | B33: $ | C33: 0 | D33: =C33 -> 0 | E33: =C33 -> 0 | F33: VERIFIED | G33: No reward is offered today
A34: Retention (all ASSUMPTIONS: no cohort exists yet)
A35: Monthly churn, Lite | B35: %/mo | C35: 0.12 | D35: 0.09 | E35: 0.07 | F35: ASSUMPTION | G35: Fix churn causes before expanding acquisition (RETENTION.md). Measure by cohort
A36: Monthly churn, Plus | B36: %/mo | C36: 0.08 | D36: 0.06 | E36: 0.05 | F36: ASSUMPTION
A37: Monthly churn, Pro | B37: %/mo | C37: 0.06 | D37: 0.045 | E37: 0.035 | F37: ASSUMPTION
A38: Expansion: add-ons, top-ups and upgrades as a share of subscription MRR | B38: % | C38: 0 | D38: 0.02 | E38: 0.05 | F38: ASSUMPTION | G38: No top-up product exists yet. Treat 0% as the only verified value
A39: Usage and cost to serve
A40: Provider cost per successful paid task (blended, from CostPerTask) | B40: $ | C40: =CostPerTask!$B$76 -> 0.0084608401 | D40: =CostPerTask!$B$76 -> 0.0084608401 | E40: =CostPerTask!$B$76 -> 0.0084608401 | F40: REPO | G40: CostPerTask sheet: real routing + list prices; tokens are assumptions
A41: Successful tasks per month, Lite customer | B41: tasks | C41: 250 | D41: 150 | E41: 120 | F41: ASSUMPTION | G41: Allowance supports ~400 moderate tasks. Measure from compute_ledger
A42: Successful tasks per month, Plus customer | B42: tasks | C42: 600 | D42: 350 | E42: 300 | F42: ASSUMPTION
A43: Successful tasks per month, Pro customer | B43: tasks | C43: 1100 | D43: 700 | E43: 600 | F43: ASSUMPTION
A44: Other metered use per month (images, Deep Research), Lite | B44: $ | C44: 0 | D44: =C44 -> 0 | E44: =C44 -> 0 | F44: REPO | G44: Lite excludes Deep Research and images (docs/lite-plan.md)
A45: Other metered use per month, Plus | B45: $ | C45: 2.5 | D45: 1.5 | E45: 1 | F45: ASSUMPTION | G45: Image High wide $0.052; Deep Research typical $2.40
A46: Other metered use per month, Pro | B46: $ | C46: 7 | D46: 4 | E46: 3 | F46: ASSUMPTION
A47: Free users: monthly drop-off | B47: %/mo | C47: 0.3 | D47: =C47 -> 0.3 | E47: =C47 -> 0.3 | F47: ASSUMPTION | G47: Measure 7/30-day return
A48: Free questions per active Free user per month | B48: q/mo | C48: 12 | D48: 8 | E48: 8 | F48: ASSUMPTION | G48: Limit is 50/day
A49: Free questions per day the free-model pool can serve | B49: q/day | C49: =CostPerTask!$B$90 -> 153.84615 | D49: =CostPerTask!$B$90 -> 153.84615 | E49: =CostPerTask!$B$90 -> 153.84615 | F49: REPO | G49: CostPerTask section F (1,000 free-model requests/day / ~6.5 per question)
A50: Cost of one overflow question on a cheap paid model | B50: $ | C50: =CostPerTask!$B$93 -> 0.0006843 | D50: =CostPerTask!$B$93 -> 0.0006843 | E50: =CostPerTask!$B$93 -> 0.0006843 | F50: REPO | G50: CostPerTask section F
A51: Serve overflow Free questions with the cheap paid fallback? 1 = yes (PROPOSAL), 0 = no (today) | B51: 0/1 | C51: 0 | D51: =C51 -> 0 | E51: =C51 -> 0 | F51: VERIFIED | G51: Today overflow is refused/degraded, not paid for. OFFER.md
A52: Fixed costs and people
A53: Fixed infrastructure per month (Vercel Pro $20 + Neon + email + domain) | B53: $/mo | C53: 60 | D53: =C53 -> 60 | E53: =C53 -> 60 | F53: ESTIMATE | G53: Vercel Pro is required for commercial use (vercel.com/docs/limits/fair-use-guidelines); not yet purchased. Neon Launch is usage-based ($0.106/CU-h, $0.35/GB-mo, neon.com/pricing)
A54: Variable infrastructure per monthly active user (paying + Free) | B54: $ | C54: 0.04 | D54: 0.03 | E54: 0.02 | F54: ASSUMPTION | G54: Functions, DB storage, bandwidth
A55: Support minutes per paying customer per month | B55: min | C55: 6 | D55: 4 | E55: 3 | F55: ASSUMPTION | G55: Count real emails/month from week 1
A56: Value of support time | B56: $/hour | C56: 30 | D56: =C56 -> 30 | E56: =C56 -> 30 | F56: ASSUMPTION | G56: Founder time is not cash today; this prices it
A57: Other fixed costs (accounting, legal, tools) | B57: $/mo | C57: 40 | D57: =C57 -> 40 | E57: =C57 -> 40 | F57: ASSUMPTION
A58: Founder pay per month (both founders) in the baseline | B58: $/mo | C58: 0 | D58: =C58 -> 0 | E58: =C58 -> 0 | F58: VERIFIED | G58: $0 today; see Profit1M for a paid-team case
A59: One-time sales (lifetime deals): never recurring, always a service obligation. OFF; proposal only
A60: Lifetime-deal units sold per month | B60: units | C60: 0 | D60: =C60 -> 0 | E60: =C60 -> 0 | F60: VERIFIED | G60: No lifetime deal exists. OFFER.md explains why it is not recommended now
A61: Lifetime-deal price | B61: $ | C61: 0 | D61: =C61 -> 0 | E61: =C61 -> 0 | F61: VERIFIED
A62: Provider cost to serve one lifetime customer per month | B62: $ | C62: =C42*C40+C45 -> 7.5765041 | D62: =D42*D40+D45 -> 4.461294 | E62: =E42*E40+E45 -> 3.538252 | F62: FORMULA | G62: Plus-level usage
A65: CONSERVATIVE SCENARIO
A66: Milestone | B66: Month reached | C66: MRR then | D66: Paying customers | E66: Qualified visits / month | F66: New payers / month | G66: Visit to paid (blended)
A67: $1,000 MRR | B67: =IFERROR(MATCH(1,$D$122:$BK$122,0),"not in 60 mo") -> not in 60 mo | C67: =IFERROR(INDEX($D$91:$BK$91,B67),"-") -> - | D67: =IFERROR(INDEX($D$88:$BK$88,B67),"-") -> - | E67: =IFERROR(INDEX($D$78:$BK$78,B67),"-") -> - | F67: =IFERROR(INDEX($D$81:$BK$81,B67),"-") -> - | G67: =IFERROR(F67/E67,"-") -> -
A68: $10,000 MRR | B68: =IFERROR(MATCH(1,$D$123:$BK$123,0),"not in 60 mo") -> not in 60 mo | C68: =IFERROR(INDEX($D$91:$BK$91,B68),"-") -> - | D68: =IFERROR(INDEX($D$88:$BK$88,B68),"-") -> - | E68: =IFERROR(INDEX($D$78:$BK$78,B68),"-") -> - | F68: =IFERROR(INDEX($D$81:$BK$81,B68),"-") -> - | G68: =IFERROR(F68/E68,"-") -> -
A69: $100,000 MRR | B69: =IFERROR(MATCH(1,$D$124:$BK$124,0),"not in 60 mo") -> not in 60 mo | C69: =IFERROR(INDEX($D$91:$BK$91,B69),"-") -> - | D69: =IFERROR(INDEX($D$88:$BK$88,B69),"-") -> - | E69: =IFERROR(INDEX($D$78:$BK$78,B69),"-") -> - | F69: =IFERROR(INDEX($D$81:$BK$81,B69),"-") -> - | G69: =IFERROR(F69/E69,"-") -> -
A70: $1M ARR run-rate ($83,333 MRR) | B70: =IFERROR(MATCH(1,$D$125:$BK$125,0),"not in 60 mo") -> not in 60 mo | C70: =IFERROR(INDEX($D$91:$BK$91,B70),"-") -> - | D70: =IFERROR(INDEX($D$88:$BK$88,B70),"-") -> - | E70: =IFERROR(INDEX($D$78:$BK$78,B70),"-") -> - | F70: =IFERROR(INDEX($D$81:$BK$81,B70),"-") -> - | G70: =IFERROR(F70/E70,"-") -> -
A71: $5M ARR run-rate ($416,667 MRR) | B71: =IFERROR(MATCH(1,$D$126:$BK$126,0),"not in 60 mo") -> not in 60 mo | C71: =IFERROR(INDEX($D$91:$BK$91,B71),"-") -> - | D71: =IFERROR(INDEX($D$88:$BK$88,B71),"-") -> - | E71: =IFERROR(INDEX($D$78:$BK$78,B71),"-") -> - | F71: =IFERROR(INDEX($D$81:$BK$81,B71),"-") -> - | G71: =IFERROR(F71/E71,"-") -> -
A74: Month | C74: 0 | D74: 1 | E74: 2 | F74: 3 | G74: 4 | H74: 5 | I74: 6 | J74: 7 | K74: 8 | L74: 9 | M74: 10 | N74: 11 | O74: 12 | P74: 13 | Q74: 14 | R74: 15 | S74: 16 | T74: 17 | U74: 18 | V74: 19 | W74: 20 | X74: 21 | Y74: 22 | Z74: 23 | AA74: 24 | AB74: 25 | AC74: 26 | AD74: 27 | AE74: 28 | AF74: 29 | AG74: 30 | AH74: 31 | AI74: 32 | AJ74: 33 | AK74: 34 | AL74: 35 | AM74: 36 | AN74: 37 | AO74: 38 | AP74: 39 | AQ74: 40 | AR74: 41 | AS74: 42 | AT74: 43 | AU74: 44 | AV74: 45 | AW74: 46 | AX74: 47 | AY74: 48 | AZ74: 49 | BA74: 50 | BB74: 51 | BC74: 52 | BD74: 53 | BE74: 54 | BF74: 55 | BG74: 56 | BH74: 57 | BI74: 58 | BJ74: 59 | BK74: 60
A75: Organic qualified visits | D75: =MIN($C$22,$C$20*(1+$C$21)^(D74-1)) -> 500 | E75: =MIN($C$22,$C$20*(1+$C$21)^(E74-1)) -> 530 | F75: =MIN($C$22,$C$20*(1+$C$21)^(F74-1)) -> 561.8 | G75: =MIN($C$22,$C$20*(1+$C$21)^(G74-1)) -> 595.508 | H75: =MIN($C$22,$C$20*(1+$C$21)^(H74-1)) -> 631.23848 | I75: =MIN($C$22,$C$20*(1+$C$21)^(I74-1)) -> 669.11279 | J75: =MIN($C$22,$C$20*(1+$C$21)^(J74-1)) -> 709.25956 | K75: =MIN($C$22,$C$20*(1+$C$21)^(K74-1)) -> 751.81513 | ... BK75: =MIN($C$22,$C$20*(1+$C$21)^(BK74-1)) -> 15560.232
A76: Paid visits (proposal, $0 today) | D76: =$C$23/$C$24 -> 0 | E76: =$C$23/$C$24 -> 0 | F76: =$C$23/$C$24 -> 0 | G76: =$C$23/$C$24 -> 0 | H76: =$C$23/$C$24 -> 0 | I76: =$C$23/$C$24 -> 0 | J76: =$C$23/$C$24 -> 0 | K76: =$C$23/$C$24 -> 0 | ... BK76: =$C$23/$C$24 -> 0
A77: Referral signups (off) | D77: =C81*$C$31*$C$32 -> 0 | E77: =D81*$C$31*$C$32 -> 0 | F77: =E81*$C$31*$C$32 -> 0 | G77: =F81*$C$31*$C$32 -> 0 | H77: =G81*$C$31*$C$32 -> 0 | I77: =H81*$C$31*$C$32 -> 0 | J77: =I81*$C$31*$C$32 -> 0 | K77: =J81*$C$31*$C$32 -> 0 | ... BK77: =BJ81*$C$31*$C$32 -> 0
A78: Qualified visits, total | D78: =D75+D76 -> 500 | E78: =E75+E76 -> 530 | F78: =F75+F76 -> 561.8 | G78: =G75+G76 -> 595.508 | H78: =H75+H76 -> 631.23848 | I78: =I75+I76 -> 669.11279 | J78: =J75+J76 -> 709.25956 | K78: =K75+K76 -> 751.81513 | ... BK78: =BK75+BK76 -> 15560.232
A79: New accounts | D79: =D78*$C$25+D77 -> 7.5 | E79: =E78*$C$25+E77 -> 7.95 | F79: =F78*$C$25+F77 -> 8.427 | G79: =G78*$C$25+G77 -> 8.93262 | H79: =H78*$C$25+H77 -> 9.4685772 | I79: =I78*$C$25+I77 -> 10.036692 | J79: =J78*$C$25+J77 -> 10.638893 | K79: =K78*$C$25+K77 -> 11.277227 | ... BK79: =BK78*$C$25+BK77 -> 233.40347
A80: Activated users | D80: =D79*$C$26 -> 2.625 | E80: =E79*$C$26 -> 2.7825 | F80: =F79*$C$26 -> 2.94945 | G80: =G79*$C$26 -> 3.126417 | H80: =H79*$C$26 -> 3.314002 | I80: =I79*$C$26 -> 3.5128421 | J80: =J79*$C$26 -> 3.7236127 | K80: =K79*$C$26 -> 3.9470294 | ... BK80: =BK79*$C$26 -> 81.691216
A81: New paying customers | C81: 0 | D81: =D80*$C$27 -> 0.065625 | E81: =E80*$C$27 -> 0.0695625 | F81: =F80*$C$27 -> 0.07373625 | G81: =G80*$C$27 -> 0.078160425 | H81: =H80*$C$27 -> 0.08285005 | I81: =I80*$C$27 -> 0.087821054 | J81: =J80*$C$27 -> 0.093090317 | K81: =K80*$C$27 -> 0.098675736 | ... BK81: =BK80*$C$27 -> 2.0422804
A82: new Lite | D82: =D81*$C$28 -> 0.04265625 | E82: =E81*$C$28 -> 0.045215625 | F82: =F81*$C$28 -> 0.047928563 | G82: =G81*$C$28 -> 0.050804276 | H82: =H81*$C$28 -> 0.053852533 | I82: =I81*$C$28 -> 0.057083685 | J82: =J81*$C$28 -> 0.060508706 | K82: =K81*$C$28 -> 0.064139228 | ... BK82: =BK81*$C$28 -> 1.3274823
A83: new Plus | D83: =D81*$C$29 -> 0.018375 | E83: =E81*$C$29 -> 0.0194775 | F83: =F81*$C$29 -> 0.02064615 | G83: =G81*$C$29 -> 0.021884919 | H83: =H81*$C$29 -> 0.023198014 | I83: =I81*$C$29 -> 0.024589895 | J83: =J81*$C$29 -> 0.026065289 | K83: =K81*$C$29 -> 0.027629206 | ... BK83: =BK81*$C$29 -> 0.57183851
A84: new Pro | D84: =D81*$C$30 -> 0.00459375 | E84: =E81*$C$30 -> 0.004869375 | F84: =F81*$C$30 -> 0.0051615375 | G84: =G81*$C$30 -> 0.0054712297 | H84: =H81*$C$30 -> 0.0057995035 | I84: =I81*$C$30 -> 0.0061474737 | J84: =J81*$C$30 -> 0.0065163222 | K84: =K81*$C$30 -> 0.0069073015 | ... BK84: =BK81*$C$30 -> 0.14295963
A85: Active Lite | C85: 0 | D85: =C85*(1-$C$35)+D82 -> 0.04265625 | E85: =D85*(1-$C$35)+E82 -> 0.082753125 | F85: =E85*(1-$C$35)+F82 -> 0.12075131 | G85: =F85*(1-$C$35)+G82 -> 0.15706543 | H85: =G85*(1-$C$35)+H82 -> 0.19207011 | I85: =H85*(1-$C$35)+I82 -> 0.22610538 | J85: =I85*(1-$C$35)+J82 -> 0.25948144 | K85: =J85*(1-$C$35)+K82 -> 0.2924829 | ... BK85: =BJ85*(1-$C$35)+BK82 -> 7.8172849
A86: Active Plus | C86: 0 | D86: =C86*(1-$C$36)+D83 -> 0.018375 | E86: =D86*(1-$C$36)+E83 -> 0.0363825 | F86: =E86*(1-$C$36)+F83 -> 0.05411805 | G86: =F86*(1-$C$36)+G83 -> 0.071673525 | H86: =G86*(1-$C$36)+H83 -> 0.089137657 | I86: =H86*(1-$C$36)+I83 -> 0.10659654 | J86: =I86*(1-$C$36)+J83 -> 0.12413411 | K86: =J86*(1-$C$36)+K83 -> 0.14183258 | ... BK86: =BJ86*(1-$C$36)+BK83 -> 4.3287526
A87: Active Pro | C87: 0 | D87: =C87*(1-$C$37)+D84 -> 0.00459375 | E87: =D87*(1-$C$37)+E84 -> 0.0091875 | F87: =E87*(1-$C$37)+F84 -> 0.013797788 | G87: =F87*(1-$C$37)+G84 -> 0.01844115 | H87: =G87*(1-$C$37)+H84 -> 0.023134185 | I87: =H87*(1-$C$37)+I84 -> 0.027893607 | J87: =I87*(1-$C$37)+J84 -> 0.032736313 | K87: =J87*(1-$C$37)+K84 -> 0.037679436 | ... BK87: =BJ87*(1-$C$37)+BK84 -> 1.2618754
A88: Active paying customers | D88: =D85+D86+D87 -> 0.065625 | E88: =E85+E86+E87 -> 0.12832313 | F88: =F85+F86+F87 -> 0.18866715 | G88: =G85+G86+G87 -> 0.24718011 | H88: =H85+H86+H87 -> 0.30434195 | I88: =I85+I86+I87 -> 0.36059553 | J88: =J85+J86+J87 -> 0.41635186 | K88: =K85+K86+K87 -> 0.47199492 | ... BK88: =BK85+BK86+BK87 -> 13.407913
A89: Customers lost this month | D89: =C85*$C$35+C86*$C$36+C87*$C$37 -> 0 | E89: =D85*$C$35+D86*$C$36+D87*$C$37 -> 0.006864375 | F89: =E85*$C$35+E86*$C$36+E87*$C$37 -> 0.013392225 | G89: =F85*$C$35+F86*$C$36+F87*$C$37 -> 0.019647469 | H89: =G85*$C$35+G86*$C$36+G87*$C$37 -> 0.025688203 | I89: =H85*$C$35+H86*$C$36+H87*$C$37 -> 0.031567477 | J89: =I85*$C$35+I86*$C$36+I87*$C$37 -> 0.037333986 | K89: =J85*$C$35+J86*$C$36+J87*$C$37 -> 0.04303268 | ... BK89: =BJ85*$C$35+BJ86*$C$36+BJ87*$C$37 -> 1.2830814
A90: Subscription MRR (billed price x active) | D90: =D85*$C$6+D86*$C$7+D87*$C$8 -> 2.1387187 | E90: =E85*$C$6+E86*$C$7+E87*$C$8 -> 4.2097418 | F90: =F85*$C$6+F86*$C$7+F87*$C$8 -> 6.2282306 | G90: =G85*$C$6+G86*$C$7+G87*$C$8 -> 8.2082604 | H90: =H85*$C$6+H86*$C$7+H87*$C$8 -> 10.162972 | I90: =I85*$C$6+I86*$C$7+I87*$C$8 -> 12.104707 | J90: =J85*$C$6+J86*$C$7+J87*$C$8 -> 14.045131 | K90: =K85*$C$6+K86*$C$7+K87*$C$8 -> 15.995348 | ... BK90: =BK85*$C$6+BK86*$C$7+BK87*$C$8 -> 477.19302
A91: MRR incl. expansion (recurring only) | D91: =D90*(1+$C$38) -> 2.1387187 | E91: =E90*(1+$C$38) -> 4.2097418 | F91: =F90*(1+$C$38) -> 6.2282306 | G91: =G90*(1+$C$38) -> 8.2082604 | H91: =H90*(1+$C$38) -> 10.162972 | I91: =I90*(1+$C$38) -> 12.104707 | J91: =J90*(1+$C$38) -> 14.045131 | K91: =K90*(1+$C$38) -> 15.995348 | ... BK91: =BK90*(1+$C$38) -> 477.19302
A92: ARR run-rate = MRR x 12 (before any expense; not earnings) | D92: =D91*12 -> 25.664625 | E92: =E91*12 -> 50.516901 | F92: =F91*12 -> 74.738767 | G92: =G91*12 -> 98.499125 | H92: =H91*12 -> 121.95566 | I92: =I91*12 -> 145.25648 | J92: =J91*12 -> 168.54158 | K92: =K91*12 -> 191.94417 | ... BK92: =BK91*12 -> 5726.3163
A93: Introductory discounts given | D93: =(D82*$C$6+D83*$C$7+D84*$C$8)*$C$16*$C$17 -> 0.064161563 | E93: =(E82*$C$6+E83*$C$7+E84*$C$8)*$C$16*$C$17 -> 0.068011256 | F93: =(F82*$C$6+F83*$C$7+F84*$C$8)*$C$16*$C$17 -> 0.072091932 | G93: =(G82*$C$6+G83*$C$7+G84*$C$8)*$C$16*$C$17 -> 0.076417448 | H93: =(H82*$C$6+H83*$C$7+H84*$C$8)*$C$16*$C$17 -> 0.081002494 | I93: =(I82*$C$6+I83*$C$7+I84*$C$8)*$C$16*$C$17 -> 0.085862644 | J93: =(J82*$C$6+J83*$C$7+J84*$C$8)*$C$16*$C$17 -> 0.091014403 | K93: =(K82*$C$6+K83*$C$7+K84*$C$8)*$C$16*$C$17 -> 0.096475267 | ... BK93: =(BK82*$C$6+BK83*$C$7+BK84*$C$8)*$C$16*$C$17 -> 1.9967375
A94: Recurring billings after discounts (cash before refunds/fees) | D94: =D91-D93 -> 2.0745572 | E94: =E91-E93 -> 4.1417305 | F94: =F91-F93 -> 6.1561386 | G94: =G91-G93 -> 8.131843 | H94: =H91-H93 -> 10.081969 | I94: =I91-I93 -> 12.018844 | J94: =J91-J93 -> 13.954117 | K94: =K91-K93 -> 15.898873 | ... BK94: =BK91-BK93 -> 475.19629
A95: Refunds | D95: =D94*$C$15 -> 0.10372786 | E95: =E94*$C$15 -> 0.20708653 | F95: =F94*$C$15 -> 0.30780693 | G95: =G94*$C$15 -> 0.40659215 | H95: =H94*$C$15 -> 0.50409847 | I95: =I94*$C$15 -> 0.6009422 | J95: =J94*$C$15 -> 0.69770585 | K95: =K94*$C$15 -> 0.79494363 | ... BK95: =BK94*$C$15 -> 23.759814
A96: Net recurring revenue | D96: =D94-D95 -> 1.9708293 | E96: =E94-E95 -> 3.934644 | F96: =F94-F95 -> 5.8483317 | G96: =G94-G95 -> 7.7252509 | H96: =H94-H95 -> 9.5778709 | I96: =I94-I95 -> 11.417902 | J96: =J94-J95 -> 13.256411 | K96: =K94-K95 -> 15.103929 | ... BK96: =BK94-BK95 -> 451.43647
A97: One-time sales (lifetime deals; NOT recurring) | D97: =$C$60*$C$61 -> 0 | E97: =$C$60*$C$61 -> 0 | F97: =$C$60*$C$61 -> 0 | G97: =$C$60*$C$61 -> 0 | H97: =$C$60*$C$61 -> 0 | I97: =$C$60*$C$61 -> 0 | J97: =$C$60*$C$61 -> 0 | K97: =$C$60*$C$61 -> 0 | ... BK97: =$C$60*$C$61 -> 0
A98: Cash collected (net recurring + one-time, before processor fees) | D98: =D96+D97 -> 1.9708293 | E98: =E96+E97 -> 3.934644 | F98: =F96+F97 -> 5.8483317 | G98: =G96+G97 -> 7.7252509 | H98: =H96+H97 -> 9.5778709 | I98: =I96+I97 -> 11.417902 | J98: =J96+J97 -> 13.256411 | K98: =K96+K97 -> 15.103929 | ... BK98: =BK96+BK97 -> 451.43647
A99: Whop payment fees + disputes | D99: =D94*($C$9+$C$11*$C$12)+D88*($C$10+$C$14*$C$13)+D97*$C$9+$C$60*$C$10 -> 0.095197223 | E99: =E94*($C$9+$C$11*$C$12)+E88*($C$10+$C$14*$C$13)+E97*$C$9+$C$60*$C$10 -> 0.18908603 | F99: =F94*($C$9+$C$11*$C$12)+F88*($C$10+$C$14*$C$13)+F97*$C$9+$C$60*$C$10 -> 0.28030696 | G99: =G94*($C$9+$C$11*$C$12)+G88*($C$10+$C$14*$C$13)+G97*$C$9+$C$60*$C$10 -> 0.36953342 | H99: =H94*($C$9+$C$11*$C$12)+H88*($C$10+$C$14*$C$13)+H97*$C$9+$C$60*$C$10 -> 0.45739105 | I99: =I94*($C$9+$C$11*$C$12)+I88*($C$10+$C$14*$C$13)+I97*$C$9+$C$60*$C$10 -> 0.54446451 | J99: =J94*($C$9+$C$11*$C$12)+J88*($C$10+$C$14*$C$13)+J97*$C$9+$C$60*$C$10 -> 0.63130371 | K99: =K94*($C$9+$C$11*$C$12)+K88*($C$10+$C$14*$C$13)+K97*$C$9+$C$60*$C$10 -> 0.71842927 | ... BK99: =BK94*($C$9+$C$11*$C$12)+BK88*($C$10+$C$14*$C$13)+BK97*$C$9+$C$60*$C$10 -> 21.221121
A100: Provider cost: answers | D100: =(D85*$C$41+D86*$C$42+D87*$C$43)*$C$40 -> 0.22626137 | E100: =(E85*$C$41+E86*$C$42+E87*$C$43)*$C$40 -> 0.44524352 | F100: =(F85*$C$41+F86*$C$42+F87*$C$43)*$C$40 -> 0.65855985 | G100: =(G85*$C$41+G86*$C$42+G87*$C$43)*$C$40 -> 0.8677077 | H100: =(H85*$C$41+H86*$C$42+H87*$C$43)*$C$40 -> 1.0740844 | I100: =(I85*$C$41+I86*$C$42+I87*$C$43)*$C$40 -> 1.2790018 | J100: =(J85*$C$41+J86*$C$42+J87*$C$43)*$C$40 -> 1.4836994 | K100: =(K85*$C$41+K86*$C$42+K87*$C$43)*$C$40 -> 1.6893561 | ... BK100: =(BK85*$C$41+BK86*$C$42+BK87*$C$43)*$C$40 -> 50.254308
A101: Provider cost: images / Deep Research | D101: =D85*$C$44+D86*$C$45+D87*$C$46 -> 0.07809375 | E101: =E85*$C$44+E86*$C$45+E87*$C$46 -> 0.15526875 | F101: =F85*$C$44+F86*$C$45+F87*$C$46 -> 0.23187964 | G101: =G85*$C$44+G86*$C$45+G87*$C$46 -> 0.30827186 | H101: =H85*$C$44+H86*$C$45+H87*$C$46 -> 0.38478343 | I101: =I85*$C$44+I86*$C$45+I87*$C$46 -> 0.4617466 | J101: =J85*$C$44+J86*$C$45+J87*$C$46 -> 0.53948945 | K101: =K85*$C$44+K86*$C$45+K87*$C$46 -> 0.61833751 | ... BK101: =BK85*$C$44+BK86*$C$45+BK87*$C$46 -> 19.655009
A102: Provider cost: lifetime-deal customers (obligation) | D102: =SUM($D74:D74)*0+$C$60*D74*$C$62 -> 0 | E102: =SUM($D74:E74)*0+$C$60*E74*$C$62 -> 0 | F102: =SUM($D74:F74)*0+$C$60*F74*$C$62 -> 0 | G102: =SUM($D74:G74)*0+$C$60*G74*$C$62 -> 0 | H102: =SUM($D74:H74)*0+$C$60*H74*$C$62 -> 0 | I102: =SUM($D74:I74)*0+$C$60*I74*$C$62 -> 0 | J102: =SUM($D74:J74)*0+$C$60*J74*$C$62 -> 0 | K102: =SUM($D74:K74)*0+$C$60*K74*$C$62 -> 0 | ... BK102: =SUM($D74:BK74)*0+$C$60*BK74*$C$62 -> 0
A103: OpenRouter 5.5% credit-purchase fee | D103: =(D100+D101+D102)*$C$18 -> 0.016739532 | E103: =(E100+E101+E102)*$C$18 -> 0.033028175 | F103: =(F100+F101+F102)*$C$18 -> 0.048974172 | G103: =(G100+G101+G102)*$C$18 -> 0.064678876 | H103: =(H100+H101+H102)*$C$18 -> 0.080237731 | I103: =(I100+I101+I102)*$C$18 -> 0.095741164 | J103: =(J100+J101+J102)*$C$18 -> 0.11127539 | K103: =(K100+K101+K102)*$C$18 -> 0.12692315 | ... BK103: =(BK100+BK101+BK102)*$C$18 -> 3.8450125
A104: Gross profit = contribution after serving users | D104: =D96+D97-D99-D100-D101-D102-D103 -> 1.5545375 | E104: =E96+E97-E99-E100-E101-E102-E103 -> 3.1120175 | F104: =F96+F97-F99-F100-F101-F102-F103 -> 4.6286111 | G104: =G96+G97-G99-G100-G101-G102-G103 -> 6.115059 | H104: =H96+H97-H99-H100-H101-H102-H103 -> 7.5813743 | I104: =I96+I97-I99-I100-I101-I102-I103 -> 9.0369478 | J104: =J96+J97-J99-J100-J101-J102-J103 -> 10.490643 | K104: =K96+K97-K99-K100-K101-K102-K103 -> 11.950883 | ... BK104: =BK96+BK97-BK99-BK100-BK101-BK102-BK103 -> 356.46102
A105: Gross margin on net revenue | D105: =IF((D96+D97)>0,D104/(D96+D97),0) -> 0.78877325 | E105: =IF((E96+E97)>0,E104/(E96+E97),0) -> 0.79092734 | F105: =IF((F96+F97)>0,F104/(F96+F97),0) -> 0.79144127 | G105: =IF((G96+G97)>0,G104/(G96+G97),0) -> 0.79156769 | H105: =IF((H96+H97)>0,H104/(H96+H97),0) -> 0.7915511 | I105: =IF((I96+I97)>0,I104/(I96+I97),0) -> 0.79147184 | J105: =IF((J96+J97)>0,J104/(J96+J97),0) -> 0.79136374 | K105: =IF((K96+K97)>0,K104/(K96+K97),0) -> 0.79124332 | ... BK105: =IF((BK96+BK97)>0,BK104/(BK96+BK97),0) -> 0.78961503
...

Sheet CostPerTask
A1: Model cost per successful task (from the repo's real routing and list prices)
A2: Sources: src/lib/orchestration/{router,live-catalog,live-synthesizer,extractor,verifier}.ts, docs/cost-model.md. Prices are OpenRouter/provider list prices dated 2026-09-28 in the repo. Token counts are ASSUMPTIONS (yellow) taken from the classifier/router estimates for a ~640-token prompt; replace them with the ledger's real averages once paid traffic exists.
A4: A. Price table ($ per 1M tokens)
A5: Model | B5: Input $/1M | C5: Output $/1M | I5: Role in the pipeline
A6: deepseek-v4-flash | B6: 0.05 | C6: 0.1 | I6: panel (cheapest)
A7: gpt-6-luna | B7: 0.1 | C7: 0.5 | I7: panel + response extractor
A8: nemotron-3-super | B8: 0.08 | C8: 0.45 | I8: panel
A9: qwen3.8-flash | B9: 0.15 | C9: 0.47 | I9: panel (complex only)
A10: glm-5.3-flash | B10: 0.15 | C10: 0.5 | I10: panel (complex only)
A11: gpt-oss-20b | B11: 0.02 | C11: 0.09 | I11: simple answers + verifier
A12: gemini-3.8-flash | B12: 0.75 | C12: 3.75 | I12: synthesizer / judge
A14: B. Token and behaviour assumptions (yellow = unsupported until the compute ledger has real averages)
A15: Prompt input tokens per call (question + 600-token system/context) | B15: 640
A16: Panel answer tokens, moderate (router estimate 900) | B16: 900
A17: Panel answer tokens, complex (router estimate 1,600) | B17: 1600
A18: Simple single-model answer tokens | B18: 350
A19: Billed-output multiplier for reasoning tokens (low effort) | B19: 1.25
A20: Extractor output tokens | B20: 700
A21: Verifier output tokens | B21: 600
A22: Synthesizer extra input tokens (extraction + verification notes) | B22: 1500
A23: Synthesizer output tokens (final answer) | B23: 900
A24: Share of complex questions where the judge also runs | B24: 0.6
A25: Retry / partial-failure overhead on cost | B25: 0.06
A26: Share of runs that fail after spending | B26: 0.03
... A33: Meter margin multiplier (limits.ts METER_MARGIN) | B33: 1.1
A35: C1. Simple question (one model, nothing to compare)
A36: Call | B36: Model | C36: Tokens in | D36: Tokens out | E36: Cost $
A37: Panel answer | B37: gpt-oss-20b | C37: =$B$15 -> 640 | D37: =$B$18 -> 350 | E37: =(C37*$B$11+D37*$B$19*$C$11)/1000000 -> 5.2175e-05
A38: Total provider cost, one run | E38: =SUM(E37) -> 5.2175e-05
A40: C2. Light-moderate question (2-model panel)
A41: Call | B41: Model | C41: Tokens in | D41: Tokens out | E41: Cost $
A42: Panel answer | B42: deepseek-v4-flash | C42: =$B$15 -> 640 | D42: =$B$16 -> 900 | E42: =(C42*$B$6+D42*$B$19*$C$6)/1000000 -> 0.0001445
A43: Panel answer | B43: gpt-6-luna | C43: =$B$15 -> 640 | D43: =$B$16 -> 900 | E43: =(C43*$B$7+D43*$B$19*$C$7)/1000000 -> 0.0006265
A44: Response extractor (stances + claims) | B44: gpt-6-luna | C44: =($B$15+2*$B$16) -> 2440 | D44: =$B$20 -> 700 | E44: =(C44*$B$7+D44*$B$19*$C$7)/1000000 -> 0.0006815
A45: Verifier (cheap reviewer) | B45: gpt-oss-20b | C45: =($B$15+2*$B$16) -> 2440 | D45: =$B$21 -> 600 | E45: =(C45*$B$11+D45*$B$19*$C$11)/1000000 -> 0.0001163
A46: Synthesizer (writes the one answer) | B46: gemini-3.8-flash | C46: =($B$15+$B$22) -> 2140 | D46: =$B$23 -> 900 | E46: =(C46*$B$12+D46*$B$19*$C$12)/1000000 -> 0.00582375
A47: Total provider cost, one run | E47: =SUM(E42:E46) -> 0.00739255
A49: C3. Moderate question (3-model panel)
A50: Call | B50: Model | C50: Tokens in | D50: Tokens out | E50: Cost $
A51: Panel answer | B51: deepseek-v4-flash | C51: =$B$15 -> 640 | D51: =$B$16 -> 900 | E51: =(C51*$B$6+D51*$B$19*$C$6)/1000000 -> 0.0001445
A52: Panel answer | B52: gpt-6-luna | C52: =$B$15 -> 640 | D52: =$B$16 -> 900 | E52: =(C52*$B$7+D52*$B$19*$C$7)/1000000 -> 0.0006265
A53: Panel answer | B53: nemotron-3-super | C53: =$B$15 -> 640 | D53: =$B$16 -> 900 | E53: =(C53*$B$8+D53*$B$19*$C$8)/1000000 -> 0.00055745
A54: Response extractor (stances + claims) | B54: gpt-6-luna | C54: =($B$15+3*$B$16) -> 3340 | D54: =$B$20 -> 700 | E54: =(C54*$B$7+D54*$B$19*$C$7)/1000000 -> 0.0007715
A55: Verifier (cheap reviewer) | B55: gpt-oss-20b | C55: =($B$15+3*$B$16) -> 3340 | D55: =$B$21 -> 600 | E55: =(C55*$B$11+D55*$B$19*$C$11)/1000000 -> 0.0001343
A56: Synthesizer (writes the one answer) | B56: gemini-3.8-flash | C56: =($B$15+$B$22) -> 2140 | D56: =$B$23 -> 900 | E56: =(C56*$B$12+D56*$B$19*$C$12)/1000000 -> 0.00582375
A57: Total provider cost, one run | E57: =SUM(E51:E56) -> 0.008058
A59: C4. Complex question (5-model panel)
A60: Call | B60: Model | C60: Tokens in | D60: Tokens out | E60: Cost $
A61: Panel answer | B61: deepseek-v4-flash | C61: =$B$15 -> 640 | D61: =$B$17 -> 1600 | E61: =(C61*$B$6+D61*$B$19*$C$6)/1000000 -> 0.000232
A62: Panel answer | B62: gpt-6-luna | C62: =$B$15 -> 640 | D62: =$B$17 -> 1600 | E62: =(C62*$B$7+D62*$B$19*$C$7)/1000000 -> 0.001064
A63: Panel answer | B63: nemotron-3-super | C63: =$B$15 -> 640 | D63: =$B$17 -> 1600 | E63: =(C63*$B$8+D63*$B$19*$C$8)/1000000 -> 0.0009512
A64: Panel answer | B64: qwen3.8-flash | C64: =$B$15 -> 640 | D64: =$B$17 -> 1600 | E64: =(C64*$B$9+D64*$B$19*$C$9)/1000000 -> 0.001036
A65: Panel answer | B65: glm-5.3-flash | C65: =$B$15 -> 640 | D65: =$B$17 -> 1600 | E65: =(C65*$B$10+D65*$B$19*$C$10)/1000000 -> 0.001096
A66: Response extractor (stances + claims) | B66: gpt-6-luna | C66: =($B$15+5*$B$17) -> 8640 | D66: =$B$20 -> 700 | E66: =(C66*$B$7+D66*$B$19*$C$7)/1000000 -> 0.0013015
A67: Verifier (cheap reviewer) | B67: gpt-oss-20b | C67: =($B$15+5*$B$17) -> 8640 | D67: =$B$21 -> 600 | E67: =(C67*$B$11+D67*$B$19*$C$11)/1000000 -> 0.0002403
A68: Judge review (runs on a share of questions) | B68: gemini-3.8-flash | C68: =($B$15+5*$B$17+800) -> 9440 | D68: =900 -> 900 | E68: =(C68*$B$12+D68*$B$19*$C$12)/1000000*$B$24 -> 0.00677925
A69: Synthesizer (writes the one answer) | B69: gemini-3.8-flash | C69: =($B$15+$B$22) -> 2140 | D69: =$B$23 -> 900 | E69: =(C69*$B$12+D69*$B$19*$C$12)/1000000 -> 0.00582375
A70: Total provider cost, one run | E70: =SUM(E61:E69) -> 0.018524
A72: D. Blended cost per successful task (paid plans)
A73: Blended cost per run (mix-weighted) | B73: =$E$38*$B$28+$E$47*$B$29+$E$57*$B$30+$E$70*$B$31 -> 0.0078603725
A74: Mix check (must be 100%) | B74: =$B$28+$B$29+$B$30+$B$31 -> 1
A75: With retry overhead | B75: =B73*(1+$B$25) -> 0.0083319948
A76: Cost per SUCCESSFUL task (adds the cost of runs that fail after spending) | B76: =B75/(1-$B$26)*(1-$B$26+$B$26*$B$27) -> 0.0084608401
A77: Credits charged per successful task (ceil(cost x margin / $0.002)) | B77: =B76*$B$33/$B$32 -> 4.6534621
A78: Router-only estimate for comparison (panel+verifier+judge; CostAwareRouter, 2026-10-03): moderate $0.00121, complex $0.01427, simple $0.00004
A80: E. What each plan's allowance buys (docs/cost-model.md)
A81: Plan | B81: Billed $/mo (Whop) | C81: Credits / month | D81: Max provider $ (credits x $0.002 / 1.1) | E81: Successful tasks per allowance | F81: Worst-case Whop fee $ | G81: Worst-case margin $ | H81: Worst-case margin %
A82: Lite | B82: 19.99 | C82: 2400 | D82: =C82*$B$32/$B$33 -> 4.3636364 | E82: =C82/$B$77 -> 515.74504 | F82: =B82*0.027+0.3 -> 0.83973 | G82: =B82-D82-F82 -> 14.786634 | H82: =G82/B82 -> 0.73970153
A83: Plus | B83: 44.99 | C83: 6000 | D83: =C83*$B$32/$B$33 -> 10.909091 | E83: =C83/$B$77 -> 1289.3626 | F83: =B83*0.027+0.3 -> 1.51473 | G83: =B83-D83-F83 -> 32.566179 | H83: =G83/B83 -> 0.72385373
A84: Pro | B84: 99.99 | C84: 13500 | D84: =C84*$B$32/$B$33 -> 24.545455 | E84: =C84/$B$77 -> 2901.0659 | F84: =B84*0.027+0.3 -> 2.99973 | G84: =B84-D84-F84 -> 72.444815 | H84: =G84/B84 -> 0.72452061
A85: Worst case = the customer spends the whole monthly allowance (before OpenRouter's 5.5% credit fee, refunds, support). The 5-hour/weekly windows, per-request caps and cooldown limit how fast that can happen.
A87: F. Free users (free models only) and the capacity limit
A88: Free-model calls per Free question (3 panel + extractor + verifier + synthesizer + ~0.5 retry) | B88: 6.5
A89: OpenRouter free-model requests per day (account with credits purchased; 50/day without) (openrouter.ai/docs/api-reference/limits) | B89: 1000
A90: Free questions per day the whole product can serve | B90: =B89/B88 -> 153.84615
A91: Free questions per month | B91: =B90*30 -> 4615.3846
A92: USD cost of a Free question (free models) | B92: 0
A93: Cheap paid fallback for one overflow question (all six calls on gpt-oss-20b, moderate tokens) | B93: =(6*($B$15*$B$11+$B$16*$B$19*$C$11)/1000000) -> 0.0006843
A94: Other metered: one High-quality wide image (docs/cost-model.md table price) | B94: 0.052
A95: Other metered: one Deep Research run, typical (docs/cost-model.md) | B95: 2.4
A97: Every free question uses the same pool of free-model requests. More Free users do not raise the pool: the product serves about the number in the 'per day' row, then answers degrade or are refused. This is the biggest scale limit on a Free-led funnel (docs/growth/BASELINE.md).

Sheet Profit1M
A1: What it takes to earn $1,000,000 a year in operating profit (a structure, not a forecast)
A2: Steady state: contribution per paying customer per month, minus fixed costs and pay, must add up to the target. Two cases per scenario: (A) before any pay to the founders, (B) after paying the team the amounts in the yellow cells. Change any blue cell.
A4: Target annual operating profit | B4: 1000000
A5: Team cost per year in case B (2 founders + 1 support/contract hire; ASSUMPTION) | B5: 330000
A6: Marketing per month in case B (paid acquisition is a proposal; ASSUMPTION) | B6: 5000
A8: Per paying customer, per month | B8: Conservative | C8: Base | D8: Ambitious
A9: Blended billed revenue (mix x price x (1+expansion)) | B9: =(Model!$C$28*Model!$C$6+Model!$C$29*Model!$C$7+Model!$C$30*Model!$C$8)*(1+Model!$C$38) -> 32.59 | C9: =(Model!$D$28*Model!$D$6+Model!$D$29*Model!$D$7+Model!$D$30*Model!$D$8)*(1+Model!$D$38) -> 37.4748 | D9: =(Model!$E$28*Model!$E$6+Model!$E$29*Model!$E$7+Model!$E$30*Model!$E$8)*(1+Model!$E$38) -> 44.0895
A10: less refunds | B10: =-B9*Model!$C$15 -> -1.6295 | C10: =-C9*Model!$D$15 -> -1.124244 | D10: =-D9*Model!$E$15 -> -0.88179
A11: less payment fees and disputes | B11: =-(B9*(Model!$C$9+Model!$C$11*Model!$C$12)+Model!$C$10+Model!$C$14*Model!$C$13) -> -1.484355 | C11: =-(C9*(Model!$D$9+Model!$D$11*Model!$D$12)+Model!$D$10+Model!$D$14*Model!$D$13) -> -1.6228806 | D11: =-(D9*(Model!$E$9+Model!$E$11*Model!$E$12)+Model!$E$10+Model!$E$14*Model!$E$13) -> -1.8360877
A12: less provider cost: answers | B12: =-(Model!$C$28*Model!$C$41+Model!$C$29*Model!$C$42+Model!$C$30*Model!$C$43)*Model!$C$40 -> -3.4477924 | C12: =-(Model!$D$28*Model!$D$41+Model!$D$29*Model!$D$42+Model!$D$30*Model!$D$43)*Model!$D$40 -> -2.326731 | D12: =-(Model!$E$28*Model!$E$41+Model!$E$29*Model!$E$42+Model!$E$30*Model!$E$43)*Model!$E$40 -> -2.2336618
A13: less provider cost: images / Deep Research | B13: =-(Model!$C$28*Model!$C$44+Model!$C$29*Model!$C$45+Model!$C$30*Model!$C$46) -> -1.19 | C13: =-(Model!$D$28*Model!$D$44+Model!$D$29*Model!$D$45+Model!$D$30*Model!$D$46) -> -0.925 | D13: =-(Model!$E$28*Model!$E$44+Model!$E$29*Model!$E$45+Model!$E$30*Model!$E$46) -> -0.85
A14: less OpenRouter 5.5% fee | B14: =(B12+B13)*Model!$C$18 -> -0.25507858 | C14: =(C12+C13)*Model!$D$18 -> -0.17884521 | D14: =(D12+D13)*Model!$E$18 -> -0.1696014
A15: less support (time valued) | B15: =-Model!$C$55/60*Model!$C$56 -> -3 | C15: =-Model!$D$55/60*Model!$D$56 -> -2 | D15: =-Model!$E$55/60*Model!$E$56 -> -1.5
A16: less variable infrastructure (paying customer only) | B16: =-Model!$C$54 -> -0.04 | C16: =-Model!$D$54 -> -0.03 | D16: =-Model!$E$54 -> -0.02
A17: Contribution per paying customer per month (sum of the lines above) | B17: =SUM(B9:B16) -> 21.543274 | C17: =SUM(C9:C16) -> 29.267099 | D17: =SUM(D9:D16) -> 36.598359
A19: Required structure | B19: Conservative | C19: Base | D19: Ambitious
A20: A. Fixed costs per year before founder pay | B20: =(Model!$C$53+Model!$C$57)*12 -> 1200 | C20: =(Model!$D$53+Model!$D$57)*12 -> 1200 | D20: =(Model!$E$53+Model!$E$57)*12 -> 1200
A21: A. Paying customers needed | B21: =($B$4+B20)/(B17*12) -> 3872.8251 | C21: =($B$4+C20)/(C17*12) -> 2850.7551 | D21: =($B$4+D20)/(D17*12) -> 2279.7015
A22: A. MRR needed | B22: =B21*B9 -> 126215.37 | C22: =C21*C9 -> 106831.48 | D22: =D21*D9 -> 100510.9
A23: A. ARR run-rate needed | B23: =B22*12 -> 1514584.5 | C23: =C22*12 -> 1281977.7 | D23: =D22*12 -> 1206130.8
A24: A. New payers per month just to replace churn | B24: =B21*B32 -> 405.09751 | C24: =C21*C32 -> 213.80664 | D24: =D21*D32 -> 129.37306
A25: A. Qualified visits per month to replace churn (visit-to-paid from scenario) | B25: =B24/B33 -> 3086457.2 | C25: =C24/C33 -> 475125.86 | D25: =D24/D33 -> 84008.48
A26: B. Fixed + team + marketing per year | B26: =B20+$B$5+$B$6*12 -> 391200 | C26: =C20+$B$5+$B$6*12 -> 391200 | D26: =D20+$B$5+$B$6*12 -> 391200
A27: B. Paying customers needed | B27: =($B$4+B26)/(B17*12) -> 5381.4166 | C27: =($B$4+C26)/(C17*12) -> 3961.2171 | D27: =($B$4+D26)/(D17*12) -> 3167.7194
A28: B. MRR needed | B28: =B27*B9 -> 175380.37 | C28: =C27*C9 -> 148445.82 | D28: =D27*D9 -> 139663.17
A29: B. ARR run-rate needed | B29: =B28*12 -> 2104564.4 | C29: =C28*12 -> 1781349.8 | D29: =D28*12 -> 1675958
A30: B. New payers per month to replace churn | B30: =B27*B32 -> 562.89618 | C30: =C27*C32 -> 297.09128 | D30: =D27*D32 -> 179.76808
A31: B. Qualified visits per month to replace churn | B31: =B30/B33 -> 4288732.8 | C31: =C30/C33 -> 660202.85 | D31: =D30/D33 -> 116732.52
A32: Blended monthly churn | B32: =Model!$C$28*Model!$C$35+Model!$C$29*Model!$C$36+Model!$C$30*Model!$C$37 -> 0.1046 | C32: =Model!$D$28*Model!$D$35+Model!$D$29*Model!$D$36+Model!$D$30*Model!$D$37 -> 0.075 | D32: =Model!$E$28*Model!$E$35+Model!$E$29*Model!$E$36+Model!$E$30*Model!$E$37 -> 0.05675
A33: Visit to paid conversion | B33: =Model!$C$25*Model!$C$26*Model!$C$27 -> 0.00013125 | C33: =Model!$D$25*Model!$D$26*Model!$D$27 -> 0.00045 | D33: =Model!$E$25*Model!$E$26*Model!$E$27 -> 0.00154
A34: Contribution margin on billed revenue | B34: =B17/B9 -> 0.6610394 | C34: =C17/C9 -> 0.7809808 | D34: =D17/D9 -> 0.8300924
A36: Notes: (1) Operating profit here is a steady-state cash view, before income tax. (2) It ignores the ramp: reaching these customer counts takes time and a growing audience (see Milestones). (3) Marketing in case B is a placeholder for a budget that does not exist; paid acquisition is a proposal. (4) Heavy users, price changes, refunds above plan and free-model capacity are not stress-tested here: change the blue inputs on Model.

Sheet Illustration
A1: The 2,000 / 10,000 customer illustration: run rate, not earnings
A2: Customers x price, annualized, is a revenue RUN RATE before any expense. It is a goal to be tested, not a forecast, and not profit. The lower half subtracts the Base-scenario cost to serve one Plus customer.
B4: 2,000 customers | C4: 10,000 customers
A5: Paying customers | B5: 2000 | C5: 10000
A6: Price per month used in the illustration ($45 Plus; Whop bills $44.99) | B6: 45 | C6: 45
A7: MRR | B7: =B5*B6 -> 90000 | C7: =C5*C6 -> 450000
A8: ARR run-rate (MRR x 12) BEFORE expenses | B8: =B7*12 -> 1080000 | C8: =C7*12 -> 5400000
A10: Same customers at Base-scenario unit costs, per month
A11: Refunds | B11: =-B7*Model!$D$15 -> -2700 | C11: =-C7*Model!$D$15 -> -13500
A12: Payment fees (2.7% + $0.30, international share, disputes) | B12: =-(B7*(Model!$D$9+Model!$D$11*Model!$D$12)+B5*(Model!$D$10+Model!$D$14*Model!$D$13)) -> -3765 | C12: =-(C7*(Model!$D$9+Model!$D$11*Model!$D$12)+C5*(Model!$D$10+Model!$D$14*Model!$D$13)) -> -18825
A13: Provider cost: answers (Plus usage) | B13: =-B5*Model!$D$42*Model!$D$40 -> -5922.5881 | C13: =-C5*Model!$D$42*Model!$D$40 -> -29612.94
A14: Provider cost: images / Deep Research (Plus) | B14: =-B5*Model!$D$45 -> -3000 | C14: =-C5*Model!$D$45 -> -15000
A15: OpenRouter 5.5% fee | B15: =(B13+B14)*Model!$D$18 -> -490.74235 | C15: =(C13+C14)*Model!$D$18 -> -2453.7117
A16: Support (time valued) | B16: =-B5*Model!$D$55/60*Model!$D$56 -> -4000 | C16: =-C5*Model!$D$55/60*Model!$D$56 -> -20000
A17: Infrastructure (fixed + variable) | B17: =-(Model!$D$53+Model!$D$54*B5*2) -> -180 | C17: =-(Model!$D$53+Model!$D$54*C5*2) -> -660
A18: Other fixed | B18: =-Model!$D$57 -> -40 | C18: =-Model!$D$57 -> -40
A19: Operating profit per month (before founder pay and income tax) | B19: =B7+SUM(B11:B18) -> 69901.67 | C19: =C7+SUM(C11:C18) -> 349908.35
A20: Operating profit per year | B20: =B19*12 -> 838820.03 | C20: =C19*12 -> 4198900.2
A21: Share of the run rate that is profit | B21: =B20/B8 -> 0.77668522 | C21: =C20/C8 -> 0.77757411
A23: Not modeled here: acquisition cost, price changes, churn replacement, free-model capacity limit (about 150 Free questions a day product-wide today), and Vercel/Neon cost growth at that scale.

Sheet Proposals
A1: Costed proposals (nothing here is live; no billing or price changes)
A3: 1. Referral reward (proposal): invitee and referrer each get bonus credits after the invitee's first activated answer
A4: Bonus credits per person (a credit = $0.002 of provider cost x 1.1 margin) | B4: 300
A5: Provider cost if fully used, per person | B5: =B4*0.002/1.1 -> 0.54545455
A6: Persons rewarded per qualifying referral (referrer + invitee) | B6: 2
A7: Max rewarded referrals per referrer | B7: 5
A8: Cost per qualifying referral if fully used | B8: =B5*B6 -> 1.0909091
A9: Maximum exposure per referrer | B9: =B8*B7 -> 5.4545455
A10: Assumed abuse / fake-account share (adds to cost; verification required) | B10: 0.25
A11: Exposure per referrer incl. abuse allowance | B11: =B9*(1+B10) -> 6.8181818
A12: Referrers in a first test (cap) | B12: 50
A13: MAXIMUM total exposure of a capped test | B13: =B11*B12 -> 340.90909
A14: Break-even: one Lite payer's contribution over 3 months (Base) | B14: =3*(Model!$D$6*(1-Model!$D$15)-(Model!$D$6*Model!$D$9+Model!$D$10)-Model!$D$41*Model!$D$40*(1+Model!$D$18)) -> 51.634926
A16: Eligibility: signed-in, email-verified, one reward per payer, invitee must be a new account that completes a real answer; rewards are credits (no cash) and expire in 30 days. Stop if exposure > cap or if fewer than 1 in 10 rewarded invitees activates.
A18: 2. Lifetime deal (NOT recommended now): cash is one-time; the service obligation is not
A19: Price | B19: 149
A20: Units sold in the test | B20: 100
A21: Cash collected (one-time; never recurring) | B21: =B19*B20 -> 14900
A22: Payment fees on that cash | B22: =B20*(B19*Model!$D$9+Model!$D$10) -> 432.3
A23: Monthly provider cost to serve one lifetime customer (Lite-level usage, Base) | B23: =Model!$D$41*Model!$D$40*(1+Model!$D$18) -> 1.338928
A24: Months the obligation is assumed to last | B24: 36
A25: Service obligation = units x monthly cost x months | B25: =B20*B23*B24 -> 4820.1406
A26: Cash minus fees minus obligation (before support and infra) | B26: =B21-B22-B25 -> 9647.5594
A27: Break-even months of service at this price | B27: =(B19-B19*Model!$D$9-Model!$D$10)/B23 -> 108.05436
A29: Counting rule: lifetime-deal cash appears only in 'one-time sales' and 'cash collected'. It is never added to MRR or ARR. A lifetime customer adds provider cost every month for as long as the product runs.

Sheet Assumptions
A1: ID | B1: Unsupported assumption (no Keplar data yet) | C1: Experiment that validates it (see docs/growth/EXPERIMENTS.md) | D1: Decision it affects
A2: E1 | B2: Qualified visits per month and their growth | C2: Publish the developer page + 2 search guides; read /admin/growth qualified visits weekly for 4 weeks | D2: Which scenario column is realistic
A3: E2 | B3: Demo-clip distribution produces qualified visits | C3: Post 4 real-run clips (founder accounts, no ads); count visits by utm | D3: Keep or stop channel 2
A4: E3 | B4: Visit to account created, account to activated | C4: First 100 activated users stage gate; funnel in /admin/growth | D4: Landing/onboarding fixes
A5: E4 | B5: Activated to paying conversion at current prices | C5: First 10 paying customers stage gate; ask research questions 8-10 | D5: Price/plan boundary proposals
A6: E5 | B6: Lite vs Plus plan mix | C6: Record plan on every payment | D6: Whether Plus ($44.99) is the right middle
A7: E6 | B7: Monthly churn by plan | C7: Cohort retention by plan after 60 days; cancellation reasons | D7: Retention work before acquisition
A8: E7 | B8: Tasks per month and other metered use per customer | C8: compute_ledger average per plan after 30 days of paid use | D8: Plan limits, heavy-user policy
A9: E8 | B9: Refund rate, dispute rate, international share | C9: Whop payments report after 20 payments | D9: Fee assumptions, refund policy
A10: E9 | B10: Free-model capacity covers Free demand | C10: Daily Free question count vs ~150 capacity; error rate 'limit' | D10: Free capacity fix / cheap fallback
A11: E10 | B11: Support minutes per customer | C11: Count emails and minutes for 30 days | D11: Support cost, tooling
A12: E11 | B12: Cost per visit of any paid channel | C12: Only after a budget, loss limit and authorization: capped test | D12: Whether paid acquisition is ever justified
